jollyjumper
