Metadata-Version: 1.2
Name: jollyjumper
Version: 0.2.0
Summary: Enjambment tool for Spanish texts
Home-page: https://github.com/linhd-postdata/jollyjumper
Author: LINHD POSTDATA Project
Author-email: info@linhd.uned.es
License: Apache Software License 2.0
Project-URL: Documentation, https://jollyjumper.readthedocs.io/
Project-URL: Changelog, https://jollyjumper.readthedocs.io/en/latest/changelog.html
Project-URL: Issue Tracker, https://github.com/linhd-postdata/jollyjumper/issues
Platform: UNKNOWN
Classifier: Development Status :: 5 - Production/Stable
Classifier: Intended Audience :: Developers
Classifier: License :: OSI Approved :: Apache Software License
Classifier: Operating System :: Unix
Classifier: Operating System :: POSIX
Classifier: Operating System :: Microsoft :: Windows
Classifier: Programming Language :: Python
Classifier: Programming Language :: Python :: 3
Classifier: Programming Language :: Python :: 3.7
Classifier: Programming Language :: Python :: Implementation :: CPython
Classifier: Topic :: Utilities
Requires-Python: >2.7, !=3.0.*, !=3.1.*, !=3.2.*, !=3.3.*
